retell/__init__.py
retell/_base_client.py
retell/_client.py
retell/_compat.py
retell/_constants.py
retell/_exceptions.py
retell/_files.py
retell/_models.py
retell/_qs.py
retell/_resource.py
retell/_response.py
retell/_streaming.py
retell/_types.py
retell/_version.py
retell/py.typed
retell/_utils/__init__.py
retell/_utils/_compat.py
retell/_utils/_datetime_parse.py
retell/_utils/_logs.py
retell/_utils/_proxy.py
retell/_utils/_reflection.py
retell/_utils/_resources_proxy.py
retell/_utils/_streams.py
retell/_utils/_sync.py
retell/_utils/_transform.py
retell/_utils/_typing.py
retell/_utils/_utils.py
retell/lib/.keep
retell/lib/__init__.py
retell/lib/webhook_auth.py
retell/resources/__init__.py
retell/resources/agent.py
retell/resources/batch_call.py
retell/resources/call.py
retell/resources/chat.py
retell/resources/chat_agent.py
retell/resources/concurrency.py
retell/resources/conversation_flow.py
retell/resources/conversation_flow_component.py
retell/resources/knowledge_base.py
retell/resources/llm.py
retell/resources/mcp_tool.py
retell/resources/phone_number.py
retell/resources/tests.py
retell/resources/voice.py
retell/types/__init__.py
retell/types/agent_create_params.py
retell/types/agent_get_versions_response.py
retell/types/agent_list_params.py
retell/types/agent_list_response.py
retell/types/agent_response.py
retell/types/agent_retrieve_params.py
retell/types/agent_update_params.py
retell/types/batch_call_create_batch_call_params.py
retell/types/batch_call_response.py
retell/types/batch_test_response.py
retell/types/call_create_phone_call_params.py
retell/types/call_create_web_call_params.py
retell/types/call_list_params.py
retell/types/call_list_response.py
retell/types/call_register_phone_call_params.py
retell/types/call_response.py
retell/types/call_update_params.py
retell/types/chat_agent_create_params.py
retell/types/chat_agent_get_versions_response.py
retell/types/chat_agent_list_params.py
retell/types/chat_agent_list_response.py
retell_sdk-5.11.0.dist-info/METADATA
retell_sdk-5.11.0.dist-info/WHEEL
retell_sdk-5.11.0.dist-info/licenses/LICENSE
retell_sdk-5.11.0.dist-info/RECORD
